pycinga/__init__.py
pycinga/perf_data.py
pycinga/plugin.py
pycinga/range.py
pycinga/response.py
pycinga/status.py
pycinga-1.0.0.dist-info/DESCRIPTION.rst
pycinga-1.0.0.dist-info/METADATA
pycinga-1.0.0.dist-info/RECORD
pycinga-1.0.0.dist-info/WHEEL
pycinga-1.0.0.dist-info/metadata.json
pycinga-1.0.0.dist-info/top_level.txt
