Metadata-Version: 2.0
Name: pycinga
Version: 1.0.0
Summary: Python library to write Icinga plugins.
Home-page: https://github.com/hurricanelabs/python-pycinga
Author: Steve McMaster
Author-email: mcmaster@hurricanelabs.com
License: MIT License
Keywords: nagios,pynagios,icinga,pycinga,monitoring
Platform: UNKNOWN
Classifier: Development Status :: 4 - Beta
Classifier: Intended Audience :: System Administrators
Classifier: License :: OSI Approved :: MIT License
Classifier: Operating System :: OS Independent
Classifier: Programming Language :: Python
Classifier: Topic :: System :: Systems Administration
